deksoftware-0.1.101.dist-info/METADATA
deksoftware-0.1.101.dist-info/WHEEL
deksoftware-0.1.101.dist-info/entry_points.txt
deksoftware/click/__entry__.py
deksoftware/click/__init__.py
deksoftware/core/__init__.py
deksoftware/core/installer/__init__.py
deksoftware/core/installer/base/__init__.py
deksoftware/core/installer/bash.py
deksoftware/core/installer/helm.py
deksoftware/core/installer/kubectl.py
deksoftware/core/installer/nerdctl.py
deksoftware/core/installer/tmux/__init__.py
deksoftware/core/installer/tmux/base/__init__.py
deksoftware/core/installer/tmux/continuum.py
deksoftware/core/installer/tmux/resurrect.py
deksoftware/core/installer/whl.py
deksoftware/core/package/__init__.py
deksoftware/core/package/base/__init__.py
deksoftware/core/package/default.py
deksoftware/core/package/generic.py
deksoftware/core/package/gh.py
deksoftware/core/package/pypi.py
deksoftware/core/repository.py
deksoftware/resources/index.yaml
deksoftware/resources/lock/libvirt.txt
deksoftware/resources/shell/diskexpend.sh
deksoftware/resources/shell/history.sh
deksoftware/resources/shell/libvirt.sh
deksoftware/resources/shell/node.sh
deksoftware/resources/shell/sinicization.sh
deksoftware-0.1.101.dist-info/RECORD
