Metadata-Version: 2.1
Name: deksoftware
Version: 0.1.101
Author-Email: sanzenwin <sanzenwin@gmail.com>
License: MIT
Requires-Python: >=3.7
Requires-Dist: dektools[version]<1.0.0
Requires-Dist: dekartifacts<1.0.0
